smart_home_testbed/__init__.py
smart_home_testbed/DeviceControl/CameraControl.py
smart_home_testbed/DeviceControl/CameraErrorControl.py
smart_home_testbed/DeviceControl/DeviceControl.py
smart_home_testbed/DeviceControl/LightControl.py
smart_home_testbed/DeviceControl/PlugControl.py
smart_home_testbed/DeviceControl/SmartThingsControl.py
smart_home_testbed/DeviceControl/SmartThingsLightControl.py
smart_home_testbed/DeviceControl/SmartThingsPlugControl.py
smart_home_testbed/DeviceControl/TapoControl.py
smart_home_testbed/DeviceControl/TapoPlugControl.py
smart_home_testbed/DeviceControl/TuyaControl.py
smart_home_testbed/DeviceControl/__init__.py
smart_home_testbed/DeviceState/AsyncDeviceState.py
smart_home_testbed/DeviceState/CameraScreenshotState.py
smart_home_testbed/DeviceState/CameraState.py
smart_home_testbed/DeviceState/DeviceState.py
smart_home_testbed/DeviceState/HueState.py
smart_home_testbed/DeviceState/LightState.py
smart_home_testbed/DeviceState/ScreenshotState.py
smart_home_testbed/DeviceState/SmartThingsState.py
smart_home_testbed/DeviceState/TapoLightState.py
smart_home_testbed/DeviceState/TapoPlugState.py
smart_home_testbed/DeviceState/TapoState.py
smart_home_testbed/DeviceState/TpLinkPlugState.py
smart_home_testbed/DeviceState/__init__.py
smart_home_testbed/devices/__init__.py
smart_home_testbed/devices/device_lifecycle.py
smart_home_testbed/devices/cameras/__init__.py
smart_home_testbed/devices/cameras/DLinkCamera/DLinkCamera.py
smart_home_testbed/devices/cameras/DLinkCamera/__init__.py
smart_home_testbed/devices/cameras/TapoCamera/TapoCamera.py
smart_home_testbed/devices/cameras/TapoCamera/__init__.py
smart_home_testbed/devices/cameras/TapoCameraSmartThings/TapoCameraSmartThings.py
smart_home_testbed/devices/cameras/TapoCameraSmartThings/__init__.py
smart_home_testbed/devices/cameras/XiaomiCamera/XiaomiCamera.py
smart_home_testbed/devices/cameras/XiaomiCamera/__init__.py
smart_home_testbed/devices/lights/__init__.py
smart_home_testbed-0.10.0.dist-info/METADATA
smart_home_testbed-0.10.0.dist-info/WHEEL
smart_home_testbed-0.10.0.dist-info/top_level.txt
smart_home_testbed-0.10.0.dist-info/RECORD
