Metadata-Version: 2.4
Name: smart-home-testbed
Version: 0.10.0
Summary: Various smart home devices' APIs
Author-email: François De Keersmaeker <francois.dekeersmaeker+github@proton.me>
Maintainer-email: François De Keersmaeker <francois.dekeersmaeker+github@proton.me>
License-Expression: GPL-3.0-or-later
Project-URL: Homepage, https://github.com/smart-home-network-security/smart-home-testbed
Project-URL: Source, https://github.com/smart-home-network-security/smart-home-testbed
Keywords: iot,smart home,api
Classifier: Development Status :: 3 - Alpha
Classifier: Programming Language :: Python :: 3
Classifier: Programming Language :: Python :: 3.8
Classifier: Programming Language :: Python :: 3.9
Classifier: Programming Language :: Python :: 3.10
Classifier: Programming Language :: Python :: 3.11
Classifier: Programming Language :: Python :: 3.12
Classifier: Programming Language :: Python :: 3 :: Only
Classifier: Operating System :: OS Independent
Requires-Python: >=3.8
Requires-Dist: pure-python-adb==0.3.0.dev0
Requires-Dist: asyncio==3.4.3
Requires-Dist: opencv-python==4.12.0.88
Requires-Dist: scikit-image==0.25.2
Requires-Dist: python-kasa==0.10.2
Requires-Dist: tapo==0.8.3
Requires-Dist: pytapo==3.3.49
Requires-Dist: aiohue==4.7.4
Requires-Dist: python-miio==0.5.12
Requires-Dist: pysmartthings==3.2.8
